pycontinuum/__init__.py
pycontinuum/endgame.py
pycontinuum/monodromy.py
pycontinuum/parameter_homotopy.py
pycontinuum/polynomial.py
pycontinuum/solver.py
pycontinuum/start_systems.py
pycontinuum/tracking.py
pycontinuum/utils.py
pycontinuum/visualization.py
pycontinuum/witness_set.py
pycontinuum-0.1.1.dist-info/LICENSE
pycontinuum-0.1.1.dist-info/METADATA
pycontinuum-0.1.1.dist-info/WHEEL
pycontinuum-0.1.1.dist-info/top_level.txt
pycontinuum-0.1.1.dist-info/RECORD
